src/__init__.py
src/audio.py
src/server.py
LangVoice-0.0.0.dist-info/METADATA
LangVoice-0.0.0.dist-info/WHEEL
LangVoice-0.0.0.dist-info/top_level.txt
LangVoice-0.0.0.dist-info/RECORD
